philh_myftp_biz/__init__.py
philh_myftp_biz/array.py
philh_myftp_biz/classOBJ.py
philh_myftp_biz/db.py
philh_myftp_biz/file.py
philh_myftp_biz/json.py
philh_myftp_biz/modules.py
philh_myftp_biz/num.py
philh_myftp_biz/pc.py
philh_myftp_biz/process.py
philh_myftp_biz/programs.py
philh_myftp_biz/terminal.py
philh_myftp_biz/text.py
philh_myftp_biz/time.py
philh_myftp_biz/web.py
philh_myftp_biz-2026.1.31.dist-info/METADATA
philh_myftp_biz-2026.1.31.dist-info/WHEEL
philh_myftp_biz-2026.1.31.dist-info/RECORD
