Metadata-Version: 2.4
Name: philh_myftp_biz
Version: 2026.1.31
Summary: 
Requires-Python: >=3.14,<4.0
Classifier: Programming Language :: Python :: 3
Classifier: Programming Language :: Python :: 3.14
Requires-Dist: QuickSocketPY
Requires-Dist: browser_cookie3
Requires-Dist: bs4
Requires-Dist: configobj
Requires-Dist: dill
Requires-Dist: elevate
Requires-Dist: inputimeout
Requires-Dist: keyring
Requires-Dist: lxml
Requires-Dist: mimetype
Requires-Dist: paramiko
Requires-Dist: ping3
Requires-Dist: psutil
Requires-Dist: python-dateutil
Requires-Dist: pytz
Requires-Dist: pyyaml
Requires-Dist: qbittorrent-api
Requires-Dist: selenium
Requires-Dist: send2trash
Requires-Dist: toml
Requires-Dist: tomli_w
Requires-Dist: tqdm
